TestUssdApp/__init__.py
TestUssdApp/admin.py
TestUssdApp/apps.py
TestUssdApp/models.py
TestUssdApp/tests.py
TestUssdApp/urls.py
TestUssdApp/views.py
TestUssdApp/migrations/__init__.py
ussdframework/__init__.py
ussdframework/admin.py
ussdframework/apis.py
ussdframework/apps.py
ussdframework/built_in_functions.py
ussdframework/core.py
ussdframework/defaults.py
ussdframework/models.py
ussdframework/tasks.py
ussdframework/urls.py
ussdframework/utilities.py
ussdframework/views.py
ussdframework/filters/__init__.py
ussdframework/filters/date_filters.py
ussdframework/filters/dict_filters.py
ussdframework/filters/list_filters.py
ussdframework/filters/utility_filters.py
ussdframework/management/__init__.py
ussdframework/management/commands/__init__.py
ussdframework/management/commands/create_ussd_app.py
ussdframework/management/commands/validate_ussd_journey.py
ussdframework/migrations/0001_initial.py
ussdframework/migrations/__init__.py
ussdframework/screens/__init__.py
ussdframework/screens/custom_screen.py
ussdframework/screens/function_screen.py
ussdframework/screens/http_screen.py
ussdframework/screens/initial_screen.py
ussdframework/screens/input_screen.py
ussdframework/screens/menu_screen.py
ussdframework/screens/quit_screen.py
ussdframework/screens/router_screen.py
ussdframework/screens/serializers.py
ussdframework/screens/update_session_screen.py
ussdframework/tests/__init__.py
ussdframework/tests/test_built_in_functions.py
ussdframework/tests/test_commands.py
ussdframework/tests/test_core_functionaliyt.py
ussdframework/tests/test_custom_screen.py
ussdframework/tests/test_date_filters.py
ussdframework/tests/test_function_screen.py
ussdframework/tests/test_http_screen.py
ussdframework/tests/test_initial_screen.py
ussdframework/tests/test_input_screen.py
ussdframework/tests/test_list_screen.py
ussdframework/tests/test_menu_screen.py
ussdframework/tests/test_multi_language_support_from_session_data.py
ussdframework/tests/test_quit_screen.py
ussd_framework-0.0.2.dist-info/METADATA
ussd_framework-0.0.2.dist-info/WHEEL
ussd_framework-0.0.2.dist-info/top_level.txt
ussd_framework-0.0.2.dist-info/RECORD
