Metadata-Version: 2.1
Name: ussd-framework
Version: 0.0.2
Summary: Ussd Framework Library
Home-page: https://github.com/eliaskioni/ussdframework
Author: Elias
Author-email: eliaskioni94@gmail.com
License: MIT
Platform: UNKNOWN
Requires-Dist: django (>=1.10)
Requires-Dist: djangorestframework (>=3.5.3)
Requires-Dist: structlog (>=16.1.0)
Requires-Dist: jinja2 (>=2.8)
Requires-Dist: PyYaml (==3.12)
Requires-Dist: PyStaticConfiguration (>=0.10.2)
Requires-Dist: requests (>=2.12.3)
Requires-Dist: celery (>=4.0.0rc3)
Requires-Dist: PyConfigure (>=0.5.9)
Requires-Dist: django-annoying (==0.10.3)
